pyxart/__init__.py
pyxart/client/__init__.py
pyxart/client/client.py
pyxart/exceptions/__init__.py
pyxart/exceptions/missingkeyexception.py
pyxart/group/__init__.py
pyxart/group/art.py
pyxart/group/art_receiver.py
pyxart/group/state.py
pyxart/group/tree.py
pyxart/group/utils.py
pyxart/keys/__init__.py
pyxart/keys/keypair.py
pyxart/keys/keypaircurve25519.py
pyxart/protobuf/pyxart.proto
pyxart/server/__init__.py
pyxart/server/server.py
pyxart-0.2.1.dist-info/LICENSE.md
pyxart-0.2.1.dist-info/METADATA
pyxart-0.2.1.dist-info/WHEEL
pyxart-0.2.1.dist-info/RECORD
