Metadata-Version: 2.1
Name: pyxart
Version: 0.2.1
Summary: Python implementation of Asynchronous Ratchet Trees
Home-page: https://github.com/PranayAnchuri/pyxart/
License: MIT
Author: Pranay Anchuri
Author-email: pranay@xmtp.com
Requires-Python: >=3.7,<4.0
Classifier: License :: OSI Approved :: MIT License
Classifier: Programming Language :: Python :: 3
Classifier: Programming Language :: Python :: 3.7
Classifier: Programming Language :: Python :: 3.8
Classifier: Programming Language :: Python :: 3.9
Classifier: Programming Language :: Python :: 3.10
Classifier: Programming Language :: Python :: 3.11
Requires-Dist: XEdDSA (>=0.6,<0.7)
Requires-Dist: art (>=5.7,<6.0)
Requires-Dist: cmd2 (>=2.4.2,<3.0.0)
Requires-Dist: cryptography (>=37.0.4,<38.0.0)
Requires-Dist: google-api-python-client (>=2.45,<3.0)
Requires-Dist: grpcio (>=1.48.1,<2.0.0)
Requires-Dist: grpcio-reflection (>=1.44,<2.0)
Requires-Dist: grpcio-tools (>=1.44,<2.0)
Requires-Dist: protobuf (>=3.20,<4.0)
Requires-Dist: pynacl (>=1.5,<2.0)
Requires-Dist: pytest (>=7.1,<8.0)
Requires-Dist: rich (>=12.5.1,<13.0.0)
